datafs/__init__.py
datafs/datafs.py
datafs-0.1.1.dist-info/DESCRIPTION.rst
datafs-0.1.1.dist-info/METADATA
datafs-0.1.1.dist-info/RECORD
datafs-0.1.1.dist-info/WHEEL
datafs-0.1.1.dist-info/metadata.json
datafs-0.1.1.dist-info/top_level.txt
