Metadata-Version: 2.0
Name: datafs
Version: 0.1.1
Summary: DataFS is an abstraction layer for data storage systems. It manages file versions and metadata using a json-like storage system like AWS's DynamoDB and relies on PyFilesystem to abstract file storage, allowing you to store files locally and on the cloud in a seamless interface.
Home-page: https://github.com/ClimateImpactLab/datafs
Author: Climate Impact Lab
Author-email: UNKNOWN
License: MIT license
Keywords: datafs
Platform: UNKNOWN
Classifier: Development Status :: 2 - Pre-Alpha
Classifier: Intended Audience :: Developers
Classifier: License :: OSI Approved :: MIT License
Classifier: Natural Language :: English
Classifier: Programming Language :: Python :: 2
Classifier: Programming Language :: Python :: 2.7
Requires-Dist: fs (==0.5.4)
